tests/__init__.py
tests/tests.py
vira/__init__.py
vira/__main__.py
vira/core.old.py
vira/core.py
vira/classes/__init__.py
vira/classes/splicegraph.py
vira/classes/transcript.py
vira/classes/treader.py
vira/classes/txgroup.py
vira/utils/__init__.py
vira/utils/common.py
vira_av-1.0.1.dist-info/licenses/LICENSE
vira_av-1.0.1.dist-info/METADATA
vira_av-1.0.1.dist-info/WHEEL
vira_av-1.0.1.dist-info/entry_points.txt
vira_av-1.0.1.dist-info/top_level.txt
vira_av-1.0.1.dist-info/RECORD
