Metadata-Version: 2.4
Name: vira-av
Version: 1.0.1
Summary: VIRA: By-Reference Exon and CDS Viral Genome Annotation
Home-page: https://github.com/alevar/vira
Author: Ales Varabyou
Author-email: ales.varabyou@jhu.edu
License: GPLv3
Classifier: Programming Language :: Python :: 3
Classifier: License :: OSI Approved :: GNU General Public License v3 (GPLv3)
Classifier: Operating System :: OS Independent
Requires-Python: >=3.6
License-File: LICENSE
Requires-Dist: biopython
Requires-Dist: intervaltree
Requires-Dist: numpy
Requires-Dist: pyfaidx
Requires-Dist: pysam
Requires-Dist: setuptools
Requires-Dist: snapper
Dynamic: author
Dynamic: author-email
Dynamic: classifier
Dynamic: description
Dynamic: description-content-type
Dynamic: home-page
Dynamic: license
Dynamic: license-file
Dynamic: requires-dist
Dynamic: requires-python
Dynamic: summary
